wmd
